zmqTools/__init__.py
zmqTools/main.py
zmqTools-2021.12.10.dist-info/LICENSE
zmqTools-2021.12.10.dist-info/METADATA
zmqTools-2021.12.10.dist-info/WHEEL
zmqTools-2021.12.10.dist-info/top_level.txt
zmqTools-2021.12.10.dist-info/RECORD
