Metadata-Version: 2.1
Name: zmqTools
Version: 2021.12.10
Summary: using zmq communication
Home-page: https://gitlab.com/freestyleteam/zmqtools
Author: vinjent
Author-email: visual.starman@gmail.com
License: MIT
Platform: UNKNOWN
Classifier: License :: OSI Approved :: MIT License
Classifier: Programming Language :: Python
Classifier: Programming Language :: Python :: 3
Classifier: Programming Language :: Python :: 3.6
Classifier: Programming Language :: Python :: Implementation :: CPython
Classifier: Programming Language :: Python :: Implementation :: PyPy
License-File: LICENSE
